nepattern-1.0.1.dist-info/METADATA
nepattern-1.0.1.dist-info/WHEEL
nepattern-1.0.1.dist-info/entry_points.txt
nepattern-1.0.1.dist-info/licenses/LICENSE
nepattern/__init__.py
nepattern/base.py
nepattern/context.py
nepattern/context.pyi
nepattern/core.py
nepattern/exception.py
nepattern/func.py
nepattern/i18n/.config.json
nepattern/i18n/.lang.schema.json
nepattern/i18n/.template.json
nepattern/i18n/.template.schema.json
nepattern/i18n/__init__.py
nepattern/i18n/en-US.json
nepattern/i18n/zh-CN.json
nepattern/main.py
nepattern/util.py
nepattern-1.0.1.dist-info/RECORD
