Metadata-Version: 2.1
Name: nepattern
Version: 1.0.1
Summary: a complex pattern, support typing
Keywords: typing,pattern,converter,validator
Author-Email: RF-Tar-Railt <rf_tar_railt@qq.com>
License: MIT
Classifier: Typing :: Typed
Classifier: Development Status :: 4 - Beta
Classifier: License :: OSI Approved :: MIT License
Classifier: Programming Language :: Python :: 3.8
Classifier: Programming Language :: Python :: 3.9
Classifier: Programming Language :: Python :: 3.10
Classifier: Programming Language :: Python :: 3.11
Classifier: Operating System :: OS Independent
Project-URL: repository, https://github.com/ArcletProject/NEPattern
Requires-Python: >=3.9
Requires-Dist: typing-extensions>=4.5.0
Requires-Dist: tarina<0.7,>=0.6
